[
        {
		"name": "Prelate",
		"unitType": "Eude Fairy",
		"cost": 1000,
		"movement": 2,
		"uniqueTo": "Eucia",
		"strength": 40,
		"uniques" : ["[+100]% Strength <after discovering [Nobblesse Oblige]>","[+1] Sight","Unbuildable","May withdraw before melee ([50]%)"],
		"attackSound": "nonmetalhit",
	},
	{
		"name": "Fairy",
		"replaces": "Scout",
		"unitType": "Eude Fairy",
		"uniqueTo": "Eucia",
		"movement": 2,
		"strength": 24,
		"cost": 40,
		"attackSound": "metalhit",
	},
	{
		"name": "Paradise Fairy",
		"requiredTech": "Scientific Theory",
		"uniqueTo": "Eucia",
		"requiredResource": "Mana",
		"unitType": "Grass",
		"movement": 2,
		"strength": 36,
		"cost": 80,
		"attackSound": "metalhit",
	},
	{
		"name": "Purgatory Fairy",
		"requiredTech": "Scientific Theory",
		"uniqueTo": "Eucia",
		"requiredResource": "Mana",
		"unitType": "Fire",
		"movement": 2,
		"strength": 36,
		"cost": 80,
		"attackSound": "metalhit",
	},
	{
		"name": "Barnacle Fairy",
                "requiredTech": "Theology",
		"uniqueTo": "Eucia",
		"requiredResource": "Mana",
		"unitType": "Water",
		"movement": 2,
		"strength": 36,
		"cost": 80,
		"attackSound": "metalhit",
	},
	{
		"name": "Covalent Fairy",
		"unitType": "Eude Fairy",
		"uniqueTo": "Eucia",
		"requiredResource": "Mana",
		"movement": 2,
		"strength": 24,
		"cost": 80,
		"requiredTech": "Scientific Theory",
		"attackSound": "metalhit",
		"uniques": ["[+200]% Strength <when defending>"],
	},
	{
		"name": "Alumina Fairy",
		"unitType": "Eude Fairy",
		"uniqueTo": "Eucia",
		"requiredResource": "Mana",
		"movement": 2,
		"strength": 50,
		"cost": 240,
		"requiredTech": "Uranography",
		"attackSound": "cannon",
		"uniques": ["[+100]% Strength <when defending>"],
	},
	{
		"name": "Handy Fairy",
		"unitType": "Eude Fairy",
		"uniqueTo": "Eucia",
		"movement": 2,
		"range": 2,
		"rangedStrength": 40,
		"strength": 32,
		"cost": 150,
		"attackSound": "shot",
		"requiredTech": "Rifling",
		"uniques": ["[-75]% Strength <vs cities>",
			"[-70]% Strength <vs [Water] units>",
		"[-70]% Strength <vs [Grass] units>",
		"[-70]% Strength <vs [Fire] units>"],
	},
	{
		"name": "Fairy Gunner",
		"uniqueTo": "Eucia",
		"unitType": "Eude Fairy",
		"movement": 2,
		"range": 2,
		"rangedStrength": 50,
		"strength": 40,
		"cost": 225,
		"attackSound": "shot",
		"requiredTech": "Economic Imperialism",
		"uniques": ["[-75]% Strength <vs cities>",
			"[-40]% Strength <vs [Water] units>",
		"[-40]% Strength <vs [Grass] units>",
		"[-40]% Strength <vs [Fire] units>"],
	},
	{
		"name": "Peculiar Fairy",
		"uniqueTo": "Eucia",
		"unitType": "Eude Fairy",
		"movement": 2,
		"range": 2,
		"rangedStrength": 60,
		"strength": 50,
		"cost": 300,
		"attackSound": "shot",
		"uniques": ["[1] additional attacks per turn","[-75]% Strength <vs cities>",
			"[-40]% Strength <vs [Water] units>",
		"[-40]% Strength <vs [Grass] units>",
		"[-40]% Strength <vs [Fire] units>"],
		"requiredTech": "Automata",
	},
	{
		"name": "Bug Fairy",
		"requiredTech": "Uranography",
		"requiredResource": "Mana",
		"uniqueTo": "Eucia",
		"unitType": "Grass",
		"movement": 2,
		"strength": 85,
		"attackSound": "cannon",
	},
	{
		"name": "Hell Fairy",
		"requiredTech": "Uranography",
		"uniqueTo": "Eucia",
		"requiredResource": "Mana",
		"unitType": "Fire",
		"movement": 2,
		"strength": 85,
		"cost": 240,
		"attackSound": "cannon",
	},
	{
		"name": "Wasserleute",
		"requiredTech": "Uranography",
		"requiredResource": "Mana",
		"uniqueTo": "Eucia",
		"unitType": "Water",
		"movement": 2,
		"strength": 85,
		"cost": 240,
		"attackSound": "cannon",
	},
	{
		"name": "Fairy Militia",
		"unitType": "Eude Fairy",
		"uniqueTo": "Eucia",
		"movement": 2,
		"strength": 35,
		"cost": 100,
		"requiredTech": "Metallurgy",
		"attackSound": "metalhit",
	},
	{
		"name": "Fairy Volunteer",
		"unitType": "Eude Fairy",
		"uniqueTo": "Eucia",
		"movement": 2,
		"strength": 55,
		"cost": 180,
		"requiredTech": "Civil Defense",
		"attackSound": "shot",
	},
	{
		"name": "Vacuum Fairy",
		"requiredTech": "Automata",
		"uniqueTo": "Eucia",
		"unitType": "Grass",
		"movement": 2,
		"strength": 50,
		"cost": 200,
		"attackSound": "metalhit",
	},
	{
		"name": "Burner Fairy",
		"requiredTech": "Automata",
		"uniqueTo": "Eucia",
		"unitType": "Fire",
		"movement": 2,
		"strength": 50,
		"cost": 200,
		"attackSound": "metalhit",
	},
	{
		"name": "Sprinkler Fairy",
		"uniqueTo": "Eucia",
		"requiredTech": "Automata",
		"unitType": "Water",
		"movement": 2,
		"strength": 50,
		"cost": 200,
		"attackSound": "metalhit",
	},
	{
		"name": "Fairytale",
		"uniqueTo": "Eucia",
		"unitType": "Eude Fairy",
		"movement": 2,
		"range": 2,
		"rangedStrength": 65,
		"strength": 50,
		"cost": 200,
		"attackSound": "throw",
		"uniques": ["[+1] Sight","Must set up to ranged attack","[+100]% Strength <vs cities>"],
		"requiredTech": "Noblesse Oblige",
	}
]
